ai_stats/__init__.py
ai_stats/py.typed
gen/ai_stats_generated/__init__.py
gen/ai_stats_generated/api_client.py
gen/ai_stats_generated/api_response.py
gen/ai_stats_generated/configuration.py
gen/ai_stats_generated/exceptions.py
gen/ai_stats_generated/py.typed
gen/ai_stats_generated/rest.py
gen/ai_stats_generated/api/__init__.py
gen/ai_stats_generated/api/default_api.py
gen/ai_stats_generated/models/__init__.py
gen/ai_stats_generated/models/audio_content_part.py
gen/ai_stats_generated/models/audio_content_part_input_audio.py
gen/ai_stats_generated/models/audio_speech_request.py
gen/ai_stats_generated/models/audio_transcription_response.py
gen/ai_stats_generated/models/audio_translation_response.py
gen/ai_stats_generated/models/batch_request.py
gen/ai_stats_generated/models/batch_request_counts.py
gen/ai_stats_generated/models/batch_response.py
gen/ai_stats_generated/models/benchmark_id.py
gen/ai_stats_generated/models/chat_choice.py
gen/ai_stats_generated/models/chat_completions_request.py
gen/ai_stats_generated/models/chat_completions_request_reasoning.py
gen/ai_stats_generated/models/chat_completions_request_response_format.py
gen/ai_stats_generated/models/chat_completions_request_response_format_one_of.py
gen/ai_stats_generated/models/chat_completions_request_tool_choice.py
gen/ai_stats_generated/models/chat_completions_request_tools_inner.py
gen/ai_stats_generated/models/chat_completions_response.py
gen/ai_stats_generated/models/chat_message.py
gen/ai_stats_generated/models/chat_message_content.py
gen/ai_stats_generated/models/embedding.py
gen/ai_stats_generated/models/embeddings_request.py
gen/ai_stats_generated/models/embeddings_request_input.py
gen/ai_stats_generated/models/embeddings_response.py
gen/ai_stats_generated/models/file_response.py
gen/ai_stats_generated/models/generation_response.py
gen/ai_stats_generated/models/generation_response_usage.py
gen/ai_stats_generated/models/get_analytics200_response.py
ai_stats_py_sdk-0.2.0.dist-info/METADATA
ai_stats_py_sdk-0.2.0.dist-info/WHEEL
ai_stats_py_sdk-0.2.0.dist-info/licenses/LICENSE
ai_stats_py_sdk-0.2.0.dist-info/licenses/NOTICE
ai_stats_py_sdk-0.2.0.dist-info/RECORD
