Metadata-Version: 2.4
Name: ai-stats-py-sdk
Version: 0.2.0
Summary: Official AI Stats Gateway SDK for Python.
Project-URL: Homepage, https://ai-stats.phaseo.app
Project-URL: Documentation, https://docs.ai-stats.phaseo.app
Project-URL: Repository, https://github.com/DanielButler1/AI-Stats
Project-URL: Issues, https://github.com/DanielButler1/AI-Stats/issues
Author-email: AI Stats <danielbutler500@gmail.com>
License: MIT
License-File: LICENSE
License-File: NOTICE
Keywords: ai,gateway,llm,sdk
Classifier: License :: OSI Approved :: MIT License
Classifier: Operating System :: OS Independent
Classifier: Programming Language :: Python :: 3
Classifier: Programming Language :: Python :: 3 :: Only
Classifier: Typing :: Typed
Requires-Python: >=3.10
Requires-Dist: httpx<1.0.0,>=0.27.2
Requires-Dist: pydantic<3.0,>=2.6
Requires-Dist: python-dateutil<3.0,>=2.9
Requires-Dist: typing-extensions>=4.8.0
